odoo/addons/website_account_fiscal_position_partner_type/README.rst
odoo/addons/website_account_fiscal_position_partner_type/__init__.py
odoo/addons/website_account_fiscal_position_partner_type/__manifest__.py
odoo/addons/website_account_fiscal_position_partner_type/controllers/__init__.py
odoo/addons/website_account_fiscal_position_partner_type/controllers/main.py
odoo/addons/website_account_fiscal_position_partner_type/controllers/portal.py
odoo/addons/website_account_fiscal_position_partner_type/i18n/es.po
odoo/addons/website_account_fiscal_position_partner_type/i18n/website_account_fiscal_position_partner_type.pot
odoo/addons/website_account_fiscal_position_partner_type/models/__init__.py
odoo/addons/website_account_fiscal_position_partner_type/models/res_partner.py
odoo/addons/website_account_fiscal_position_partner_type/models/res_users.py
odoo/addons/website_account_fiscal_position_partner_type/models/website.py
odoo/addons/website_account_fiscal_position_partner_type/readme/CONFIGURE.rst
odoo/addons/website_account_fiscal_position_partner_type/readme/CONTRIBUTORS.rst
odoo/addons/website_account_fiscal_position_partner_type/readme/DESCRIPTION.rst
odoo/addons/website_account_fiscal_position_partner_type/readme/USAGE.rst
odoo/addons/website_account_fiscal_position_partner_type/static/description/icon.png
odoo/addons/website_account_fiscal_position_partner_type/static/description/index.html
odoo/addons/website_account_fiscal_position_partner_type/static/src/js/signup.js
odoo/addons/website_account_fiscal_position_partner_type/views/auth_signup_login_templates.xml
odoo/addons/website_account_fiscal_position_partner_type/views/portal_templates.xml
odoo/addons/website_account_fiscal_position_partner_type/views/website_sale.xml
odoo/addons/website_account_fiscal_position_partner_type/views/website_views.xml
odoo_addon_website_account_fiscal_position_partner_type-15.0.1.0.2.2.dist-info/METADATA
odoo_addon_website_account_fiscal_position_partner_type-15.0.1.0.2.2.dist-info/WHEEL
odoo_addon_website_account_fiscal_position_partner_type-15.0.1.0.2.2.dist-info/top_level.txt
odoo_addon_website_account_fiscal_position_partner_type-15.0.1.0.2.2.dist-info/RECORD
