Metadata-Version: 2.1
Name: odoo-addon-website-account-fiscal-position-partner-type
Version: 15.0.1.0.2.2
Summary: Website Account Fiscal Position Partner Type
Home-page: https://github.com/OCA/e-commerce
Author: Sygel Technology,Odoo Community Association (OCA)
Author-email: support@odoo-community.org
License: AGPL-3
Platform: UNKNOWN
Classifier: Programming Language :: Python
Classifier: Framework :: Odoo
Classifier: Framework :: Odoo :: 15.0
Classifier: License :: OSI Approved :: GNU Affero General Public License v3
Classifier: Development Status :: 4 - Beta
Requires-Python: >=3.8
Requires-Dist: odoo-addon-account-fiscal-position-partner-type <15.1dev,>=15.0dev
Requires-Dist: odoo <15.1dev,>=15.0a
